autograde_module/__init__.py
autograde_module/autograder.py
autograde_module/multiproccessing_extended.py
autograde_module/subprocess_controller.py
autograde_module/unittest_extensions.py
autograde_module/unittest_formatter.py
autograde_module/utils.py
autograde_module/custommagics/__init__.py
autograde_module/custommagics/custommagics.py
autograde_module/relative_import/__init__.py
autograde_module/relative_import/relative_import.py
liacs_autograder-1.0.0.5.1.dist-info/LICENSE
liacs_autograder-1.0.0.5.1.dist-info/METADATA
liacs_autograder-1.0.0.5.1.dist-info/WHEEL
liacs_autograder-1.0.0.5.1.dist-info/top_level.txt
liacs_autograder-1.0.0.5.1.dist-info/RECORD
