Metadata-Version: 2.2
Name: LIACS_Autograder
Version: 1.0.0.5.1
Summary: A package to autograde
Home-page: https://github.com/jjgsherwood/LIACS_Autograder
Author: Jonne Goedhart; Irina Epure
Author-email: j.j.goedhart@liacs.leidenuniv.nl
License: Creative Commons CC BY-NC-SA 4.0
Classifier: Programming Language :: Python :: 3
Classifier: Operating System :: OS Independent
Requires-Python: >=3.10
License-File: LICENSE
Requires-Dist: PyYAML>=6.0.1
Requires-Dist: numpy>=1.26.4
Dynamic: author
Dynamic: author-email
Dynamic: classifier
Dynamic: description
Dynamic: description-content-type
Dynamic: home-page
Dynamic: license
Dynamic: requires-dist
Dynamic: requires-python
Dynamic: summary
